{"nodes":[{"id":"doc_spec_collab","label":"COLLAB","file_type":"document","source_file":"spec/COLLAB.md","source_location":null,"source_url":null,"captured_at":null,"author":null,"contributor":null},{"id":"spec_collab_collaboration_feature_specification","label":"Collaboration Feature Specification","file_type":"document","source_file":"spec/COLLAB.md","source_location":"L1","source_url":null,"captured_at":null,"author":null,"contributor":null},{"id":"spec_collab_overview","label":"Overview","file_type":"document","source_file":"spec/COLLAB.md","source_location":"L3","source_url":null,"captured_at":null,"author":null,"contributor":null},{"id":"spec_collab_workspace_management","label":"Workspace Management","file_type":"document","source_file":"spec/COLLAB.md","source_location":"L7","source_url":null,"captured_at":null,"author":null,"contributor":null},{"id":"spec_collab_workspace_lifecycle","label":"Workspace Lifecycle","file_type":"document","source_file":"spec/COLLAB.md","source_location":"L9","source_url":null,"captured_at":null,"author":null,"contributor":null},{"id":"spec_collab_workspace_membership_roles","label":"Workspace Membership Roles","file_type":"document","source_file":"spec/COLLAB.md","source_location":"L17","source_url":null,"captured_at":null,"author":null,"contributor":null},{"id":"spec_collab_workspace_selector_ui","label":"Workspace Selector UI","file_type":"document","source_file":"spec/COLLAB.md","source_location":"L24","source_url":null,"captured_at":null,"author":null,"contributor":null},{"id":"spec_collab_workspace_members_ui","label":"Workspace Members UI","file_type":"document","source_file":"spec/COLLAB.md","source_location":"L41","source_url":null,"captured_at":null,"author":null,"contributor":null},{"id":"spec_collab_hidden_workspace_visibility","label":"Hidden Workspace Visibility","file_type":"document","source_file":"spec/COLLAB.md","source_location":"L47","source_url":null,"captured_at":null,"author":null,"contributor":null},{"id":"spec_collab_hidden_workspace_navigation_lock_ui","label":"Hidden Workspace Navigation Lock (UI)","file_type":"document","source_file":"spec/COLLAB.md","source_location":"L52","source_url":null,"captured_at":null,"author":null,"contributor":null},{"id":"spec_collab_object_edition_locks","label":"Object Edition Locks","file_type":"document","source_file":"spec/COLLAB.md","source_location":"L59","source_url":null,"captured_at":null,"author":null,"contributor":null},{"id":"spec_collab_lock_model","label":"Lock Model","file_type":"document","source_file":"spec/COLLAB.md","source_location":"L61","source_url":null,"captured_at":null,"author":null,"contributor":null},{"id":"spec_collab_lock_api","label":"Lock API","file_type":"document","source_file":"spec/COLLAB.md","source_location":"L68","source_url":null,"captured_at":null,"author":null,"contributor":null},{"id":"spec_collab_unlock_request_flow","label":"Unlock Request Flow","file_type":"document","source_file":"spec/COLLAB.md","source_location":"L82","source_url":null,"captured_at":null,"author":null,"contributor":null},{"id":"spec_collab_lock_lifecycle_sse_cleanup","label":"Lock Lifecycle (SSE + cleanup)","file_type":"document","source_file":"spec/COLLAB.md","source_location":"L89","source_url":null,"captured_at":null,"author":null,"contributor":null},{"id":"spec_collab_lock_ui","label":"Lock UI","file_type":"document","source_file":"spec/COLLAB.md","source_location":"L95","source_url":null,"captured_at":null,"author":null,"contributor":null},{"id":"spec_collab_presence_badge_all_roles","label":"Presence Badge (all roles)","file_type":"document","source_file":"spec/COLLAB.md","source_location":"L106","source_url":null,"captured_at":null,"author":null,"contributor":null},{"id":"spec_collab_sse_events","label":"SSE Events","file_type":"document","source_file":"spec/COLLAB.md","source_location":"L114","source_url":null,"captured_at":null,"author":null,"contributor":null},{"id":"spec_collab_comments","label":"Comments","file_type":"document","source_file":"spec/COLLAB.md","source_location":"L120","source_url":null,"captured_at":null,"author":null,"contributor":null},{"id":"concept_admin","label":"admin","file_type":"document","source_file":"spec/COLLAB.md","source_location":null,"source_url":null,"captured_at":null,"author":null,"contributor":null},{"id":"concept_sharewithadmin","label":"shareWithAdmin","file_type":"document","source_file":"spec/COLLAB.md","source_location":null,"source_url":null,"captured_at":null,"author":null,"contributor":null},{"id":"concept_settings_3","label":"/settings","file_type":"document","source_file":"spec/COLLAB.md","source_location":null,"source_url":null,"captured_at":null,"author":null,"contributor":null},{"id":"concept_viewer","label":"viewer","file_type":"document","source_file":"spec/COLLAB.md","source_location":null,"source_url":null,"captured_at":null,"author":null,"contributor":null},{"id":"concept_commenter","label":"commenter","file_type":"document","source_file":"spec/COLLAB.md","source_location":null,"source_url":null,"captured_at":null,"author":null,"contributor":null},{"id":"concept_editor","label":"editor","file_type":"document","source_file":"spec/COLLAB.md","source_location":null,"source_url":null,"captured_at":null,"author":null,"contributor":null},{"id":"concept_eye","label":"eye","file_type":"document","source_file":"spec/COLLAB.md","source_location":null,"source_url":null,"captured_at":null,"author":null,"contributor":null},{"id":"concept_eye_off","label":"eye-off","file_type":"document","source_file":"spec/COLLAB.md","source_location":null,"source_url":null,"captured_at":null,"author":null,"contributor":null},{"id":"concept_editableinput_2","label":"EditableInput","file_type":"document","source_file":"spec/COLLAB.md","source_location":null,"source_url":null,"captured_at":null,"author":null,"contributor":null},{"id":"concept_put_workspaces_id","label":"PUT /workspaces/:id","file_type":"document","source_file":"spec/COLLAB.md","source_location":null,"source_url":null,"captured_at":null,"author":null,"contributor":null},{"id":"concept_workspace_update","label":"workspace_update","file_type":"document","source_file":"spec/COLLAB.md","source_location":null,"source_url":null,"captured_at":null,"author":null,"contributor":null},{"id":"concept_workspace_membership_update","label":"workspace_membership_update","file_type":"document","source_file":"spec/COLLAB.md","source_location":null,"source_url":null,"captured_at":null,"author":null,"contributor":null}],"edges":[{"source":"doc_spec_collab","target":"spec_collab_collaboration_feature_specification","relation":"references","confidence":"EXTRACTED","confidence_score":1,"source_file":"spec/COLLAB.md","source_location":"L1","weight":1},{"source":"doc_spec_collab","target":"spec_collab_overview","relation":"references","confidence":"EXTRACTED","confidence_score":1,"source_file":"spec/COLLAB.md","source_location":"L3","weight":1},{"source":"doc_spec_collab","target":"spec_collab_workspace_management","relation":"references","confidence":"EXTRACTED","confidence_score":1,"source_file":"spec/COLLAB.md","source_location":"L7","weight":1},{"source":"doc_spec_collab","target":"spec_collab_workspace_lifecycle","relation":"references","confidence":"EXTRACTED","confidence_score":1,"source_file":"spec/COLLAB.md","source_location":"L9","weight":1},{"source":"doc_spec_collab","target":"spec_collab_workspace_membership_roles","relation":"references","confidence":"EXTRACTED","confidence_score":1,"source_file":"spec/COLLAB.md","source_location":"L17","weight":1},{"source":"doc_spec_collab","target":"spec_collab_workspace_selector_ui","relation":"references","confidence":"EXTRACTED","confidence_score":1,"source_file":"spec/COLLAB.md","source_location":"L24","weight":1},{"source":"doc_spec_collab","target":"spec_collab_workspace_members_ui","relation":"references","confidence":"EXTRACTED","confidence_score":1,"source_file":"spec/COLLAB.md","source_location":"L41","weight":1},{"source":"doc_spec_collab","target":"spec_collab_hidden_workspace_visibility","relation":"references","confidence":"EXTRACTED","confidence_score":1,"source_file":"spec/COLLAB.md","source_location":"L47","weight":1},{"source":"doc_spec_collab","target":"spec_collab_hidden_workspace_navigation_lock_ui","relation":"references","confidence":"EXTRACTED","confidence_score":1,"source_file":"spec/COLLAB.md","source_location":"L52","weight":1},{"source":"doc_spec_collab","target":"spec_collab_object_edition_locks","relation":"references","confidence":"EXTRACTED","confidence_score":1,"source_file":"spec/COLLAB.md","source_location":"L59","weight":1},{"source":"doc_spec_collab","target":"spec_collab_lock_model","relation":"references","confidence":"EXTRACTED","confidence_score":1,"source_file":"spec/COLLAB.md","source_location":"L61","weight":1},{"source":"doc_spec_collab","target":"spec_collab_lock_api","relation":"references","confidence":"EXTRACTED","confidence_score":1,"source_file":"spec/COLLAB.md","source_location":"L68","weight":1},{"source":"doc_spec_collab","target":"spec_collab_unlock_request_flow","relation":"references","confidence":"EXTRACTED","confidence_score":1,"source_file":"spec/COLLAB.md","source_location":"L82","weight":1},{"source":"doc_spec_collab","target":"spec_collab_lock_lifecycle_sse_cleanup","relation":"references","confidence":"EXTRACTED","confidence_score":1,"source_file":"spec/COLLAB.md","source_location":"L89","weight":1},{"source":"doc_spec_collab","target":"spec_collab_lock_ui","relation":"references","confidence":"EXTRACTED","confidence_score":1,"source_file":"spec/COLLAB.md","source_location":"L95","weight":1},{"source":"doc_spec_collab","target":"spec_collab_presence_badge_all_roles","relation":"references","confidence":"EXTRACTED","confidence_score":1,"source_file":"spec/COLLAB.md","source_location":"L106","weight":1},{"source":"doc_spec_collab","target":"spec_collab_sse_events","relation":"references","confidence":"EXTRACTED","confidence_score":1,"source_file":"spec/COLLAB.md","source_location":"L114","weight":1},{"source":"doc_spec_collab","target":"spec_collab_comments","relation":"references","confidence":"EXTRACTED","confidence_score":1,"source_file":"spec/COLLAB.md","source_location":"L120","weight":1},{"source":"spec_collab_collaboration_feature_specification","target":"concept_admin","relation":"references","confidence":"EXTRACTED","confidence_score":0.85,"source_file":"spec/COLLAB.md","source_location":null,"weight":1},{"source":"spec_collab_collaboration_feature_specification","target":"concept_sharewithadmin","relation":"references","confidence":"EXTRACTED","confidence_score":0.85,"source_file":"spec/COLLAB.md","source_location":null,"weight":1},{"source":"spec_collab_collaboration_feature_specification","target":"concept_settings_3","relation":"references","confidence":"EXTRACTED","confidence_score":0.85,"source_file":"spec/COLLAB.md","source_location":null,"weight":1},{"source":"spec_collab_collaboration_feature_specification","target":"concept_viewer","relation":"references","confidence":"EXTRACTED","confidence_score":0.85,"source_file":"spec/COLLAB.md","source_location":null,"weight":1},{"source":"spec_collab_collaboration_feature_specification","target":"concept_commenter","relation":"references","confidence":"EXTRACTED","confidence_score":0.85,"source_file":"spec/COLLAB.md","source_location":null,"weight":1},{"source":"spec_collab_collaboration_feature_specification","target":"concept_editor","relation":"references","confidence":"EXTRACTED","confidence_score":0.85,"source_file":"spec/COLLAB.md","source_location":null,"weight":1},{"source":"spec_collab_collaboration_feature_specification","target":"concept_eye","relation":"references","confidence":"EXTRACTED","confidence_score":0.85,"source_file":"spec/COLLAB.md","source_location":null,"weight":1},{"source":"spec_collab_collaboration_feature_specification","target":"concept_eye_off","relation":"references","confidence":"EXTRACTED","confidence_score":0.85,"source_file":"spec/COLLAB.md","source_location":null,"weight":1},{"source":"spec_collab_collaboration_feature_specification","target":"concept_editableinput_2","relation":"references","confidence":"EXTRACTED","confidence_score":0.85,"source_file":"spec/COLLAB.md","source_location":null,"weight":1},{"source":"spec_collab_collaboration_feature_specification","target":"concept_put_workspaces_id","relation":"references","confidence":"EXTRACTED","confidence_score":0.85,"source_file":"spec/COLLAB.md","source_location":null,"weight":1},{"source":"spec_collab_collaboration_feature_specification","target":"concept_workspace_update","relation":"references","confidence":"EXTRACTED","confidence_score":0.85,"source_file":"spec/COLLAB.md","source_location":null,"weight":1},{"source":"spec_collab_collaboration_feature_specification","target":"concept_workspace_membership_update","relation":"references","confidence":"EXTRACTED","confidence_score":0.85,"source_file":"spec/COLLAB.md","source_location":null,"weight":1}],"hyperedges":[{"id":"hyper_spec_collab","label":"COLLAB sections","nodes":["doc_spec_collab","spec_collab_collaboration_feature_specification","spec_collab_overview","spec_collab_workspace_management","spec_collab_workspace_lifecycle","spec_collab_workspace_membership_roles","spec_collab_workspace_selector_ui","spec_collab_workspace_members_ui","spec_collab_hidden_workspace_visibility"],"relation":"form","confidence":"EXTRACTED","confidence_score":0.75,"source_file":"spec/COLLAB.md"}]}